app/__init__.py
app/settings.py
app/settings_local.py
app/urls.py
repositories/__init__.py
repositories/custom_models.py
repositories/catalogo/__init__.py
repositories/catalogo/apps.py
repositories/catalogo/models.py
repositories/cliente/__init__.py
repositories/cliente/apps.py
repositories/cliente/models.py
repositories/configuracao/__init__.py
repositories/configuracao/apps.py
repositories/configuracao/models.py
repositories/domain/__init__.py
repositories/domain/apps.py
repositories/domain/models.py
repositories/faturamento/__init__.py
repositories/faturamento/apps.py
repositories/faturamento/models.py
repositories/integration/__init__.py
repositories/integration/apps.py
repositories/integration/models.py
repositories/integration/notifications.py
repositories/integration/serializers.py
repositories/integration/base/__init__.py
repositories/integration/base/notifications.py
repositories/integration/base/serializers.py
repositories/libs/__init__.py
repositories/libs/aws.py
repositories/libs/novo_template_definicoes.py
repositories/libs/utils.py
repositories/libs/correios/__init__.py
repositories/libs/correios/correios.py
repositories/marketing/__init__.py
repositories/marketing/apps.py
repositories/marketing/models.py
repositories/marketplace/__init__.py
repositories/marketplace/apps.py
repositories/marketplace/models.py
repositories/pedido/__init__.py
repositories/pedido/apps.py
repositories/pedido/models.py
repositories/plataforma/__init__.py
repositories/plataforma/apps.py
repositories/plataforma/models.py
repositories/relatorio/__init__.py
repositories/relatorio/apps.py
repositories/relatorio/models.py
li_repo-1.11.8.dist-info/METADATA
li_repo-1.11.8.dist-info/WHEEL
li_repo-1.11.8.dist-info/top_level.txt
li_repo-1.11.8.dist-info/RECORD
