Metadata-Version: 2.1
Name: li-repo
Version: 1.11.8
Summary: Loja Integrada's models for Django ORM.
Home-page: https://github.com/lojaintegrada/LI-Repo
Author: Loja Integrada
Author-email: contato@lojaintegrada.com.br
License: LIEULA
Platform: UNKNOWN
Classifier: Development Status :: 2 - Pre-Alpha
Classifier: Intended Audience :: Developers
Classifier: License :: OSI Approved :: MIT License
Classifier: Operating System :: OS Independent
Classifier: Programming Language :: Python
Classifier: Programming Language :: Python :: 2.6
Classifier: Programming Language :: Python :: 2.7
Classifier: Topic :: Software Development :: Libraries :: Python Modules
Classifier: Topic :: Internet
Requires-Dist: distribute
Requires-Dist: Django (<1.9)
Requires-Dist: jsonfield (>=0.9.20)
Requires-Dist: psycopg2
Requires-Dist: django-mptt
Requires-Dist: unidecode
Requires-Dist: boto
Requires-Dist: li-common
Requires-Dist: django-cache-machine
Requires-Dist: tldextract
